djangodb/__init__.py
djangodb/manage.py
djangodb/api/__init__.py
djangodb/api/admin.py
djangodb/api/apps.py
djangodb/api/exception.py
djangodb/api/models.py
djangodb/api/serializers.py
djangodb/api/tests.py
djangodb/api/urls.py
djangodb/api/views.py
djangodb/api/migrations/__init__.py
djangodb/user/__init__.py
djangodb/user/admin.py
djangodb/user/apps.py
djangodb/user/authentication.py
djangodb/user/models.py
djangodb/user/serializers.py
djangodb/user/tests.py
djangodb/user/urls.py
djangodb/user/views.py
djangodb/user/migrations/0001_initial.py
djangodb/user/migrations/__init__.py
djangodb/wsseptemp/__init__.py
djangodb/wsseptemp/asgi.py
djangodb/wsseptemp/settings.py
djangodb/wsseptemp/urls.py
djangodb/wsseptemp/wsgi.py
djangorestdb-0.0.2.dist-info/METADATA
djangorestdb-0.0.2.dist-info/WHEEL
djangorestdb-0.0.2.dist-info/top_level.txt
djangorestdb-0.0.2.dist-info/RECORD
