Metadata-Version: 2.1
Name: djangorestdb
Version: 0.0.2
Summary: This is the simplest module for quick work with files.
Home-page: UNKNOWN
Author: pushokmaster
License: UNKNOWN
Keywords: files speedfiles
Platform: UNKNOWN
Classifier: Programming Language :: Python :: 3.11
Classifier: License :: OSI Approved :: MIT License
Classifier: Operating System :: OS Independent
Requires-Python: >=3.6
